{
  "inheritAttrs": true,
  "errors": [],
  "warnings": [],
  "keywords": [],
  "slots": [],
  "props": [
    {
      "kind": "prop",
      "description": "数量",
      "keywords": [],
      "visibility": "public",
      "name": "value",
      "type": "String",
      "required": false,
      "describeModel": false
    },
    {
      "kind": "prop",
      "description": "可选星星数量",
      "keywords": [],
      "visibility": "public",
      "name": "count",
      "type": "String",
      "required": false,
      "describeModel": false
    },
    {
      "kind": "prop",
      "description": "禁止用户操作",
      "keywords": [],
      "visibility": "public",
      "name": "disabled",
      "type": "Boolean",
      "required": false,
      "describeModel": false
    },
    {
      "kind": "prop",
      "description": "是否只读",
      "keywords": [],
      "visibility": "public",
      "name": "readonly",
      "type": "Boolean",
      "required": false,
      "describeModel": false
    },
    {
      "kind": "prop",
      "description": "大小",
      "keywords": [],
      "visibility": "public",
      "name": "size",
      "type": "String",
      "required": false,
      "describeModel": false
    },
    {
      "kind": "prop",
      "description": "未选中颜色",
      "keywords": [],
      "visibility": "public",
      "name": "inactiveColor",
      "type": "String",
      "required": false,
      "describeModel": false
    },
    {
      "kind": "prop",
      "description": "选中颜色",
      "keywords": [],
      "visibility": "public",
      "name": "activeColor",
      "type": "String",
      "required": false,
      "describeModel": false
    },
    {
      "kind": "prop",
      "description": "距离",
      "keywords": [],
      "visibility": "public",
      "name": "gutter",
      "type": "String",
      "required": false,
      "describeModel": false
    },
    {
      "kind": "prop",
      "description": "最少选中个数",
      "keywords": [],
      "visibility": "public",
      "name": "minCount",
      "type": "String",
      "required": false,
      "describeModel": false
    },
    {
      "kind": "prop",
      "description": "允许半选择",
      "keywords": [],
      "visibility": "public",
      "name": "allowHalf",
      "type": "Boolean",
      "required": false,
      "describeModel": false
    },
    {
      "kind": "prop",
      "description": "选中时图标名",
      "keywords": [],
      "visibility": "public",
      "name": "activeIcon",
      "type": "String",
      "required": false,
      "describeModel": false
    },
    {
      "kind": "prop",
      "description": "未选中图标名",
      "keywords": [],
      "visibility": "public",
      "name": "inactiveIcon",
      "type": "String",
      "required": false,
      "describeModel": false
    },
    {
      "kind": "prop",
      "description": "是否滑动选择",
      "keywords": [],
      "visibility": "public",
      "name": "touchable",
      "type": "Boolean",
      "required": false,
      "describeModel": false
    }
  ],
  "data": [
    {
      "kind": "data",
      "description": "生成一个唯一id，否则一个页面多个评分组件，会造成冲突",
      "keywords": [],
      "visibility": "public",
      "name": "elId",
      "type": "CallExpression",
      "initialValue": "uni.$u.guid()"
    },
    {
      "kind": "data",
      "keywords": [],
      "visibility": "public",
      "name": "elClass",
      "type": "CallExpression",
      "initialValue": "uni.$u.guid()"
    },
    {
      "kind": "data",
      "keywords": [],
      "visibility": "public",
      "name": "rateBoxLeft",
      "type": "number",
      "initialValue": "0"
    },
    {
      "kind": "data",
      "description": "评分盒子左边到屏幕左边的距离，用于滑动选择时计算距离",
      "keywords": [],
      "visibility": "public",
      "name": "activeIndex",
      "type": "object",
      "initialValue": "this.value"
    },
    {
      "kind": "data",
      "keywords": [],
      "visibility": "public",
      "name": "rateWidth",
      "type": "number",
      "initialValue": "0"
    },
    {
      "kind": "data",
      "description": "标识是否正在滑动，由于iOS事件上touch比click先触发，导致快速滑动结束后，接着触发click，导致事件混乱而出错",
      "keywords": [],
      "visibility": "public",
      "name": "moving",
      "type": "boolean",
      "initialValue": "false"
    }
  ],
  "computed": [],
  "events": [
    {
      "kind": "event",
      "description": "发出change事件",
      "keywords": [],
      "visibility": "public",
      "name": "change",
      "arguments": [
        {
          "name": "activeIndex",
          "type": "any",
          "rest": false
        }
      ]
    },
    {
      "kind": "event",
      "description": "同时修改双向绑定的value的值",
      "keywords": [],
      "visibility": "public",
      "name": "input",
      "arguments": [
        {
          "name": "activeIndex",
          "type": "any",
          "rest": false
        }
      ]
    }
  ],
  "methods": [
    {
      "kind": "method",
      "keywords": [],
      "visibility": "public",
      "name": "init",
      "params": [],
      "syntax": [
        "init(): void"
      ],
      "returns": {
        "type": "void"
      }
    },
    {
      "kind": "method",
      "description": "获取评分组件盒子的布局信息",
      "keywords": [],
      "visibility": "public",
      "name": "getRateItemRect",
      "params": [],
      "syntax": [
        "async getRateItemRect(): Promise"
      ],
      "returns": {
        "type": "Promise"
      }
    },
    {
      "kind": "method",
      "description": "获取单个星星的尺寸",
      "keywords": [],
      "visibility": "public",
      "name": "getRateIconWrapRect",
      "params": [],
      "syntax": [
        "getRateIconWrapRect(): void"
      ],
      "returns": {
        "type": "void"
      }
    },
    {
      "kind": "method",
      "description": "手指滑动",
      "keywords": [],
      "visibility": "public",
      "name": "touchMove",
      "params": [
        {
          "name": "e",
          "type": "unknow",
          "rest": false
        }
      ],
      "syntax": [
        "touchMove(e: unknow): void"
      ],
      "returns": {
        "type": "void"
      }
    },
    {
      "kind": "method",
      "description": "停止滑动",
      "keywords": [],
      "visibility": "public",
      "name": "touchEnd",
      "params": [
        {
          "name": "e",
          "type": "unknow",
          "rest": false
        }
      ],
      "syntax": [
        "touchEnd(e: unknow): void"
      ],
      "returns": {
        "type": "void"
      }
    },
    {
      "kind": "method",
      "description": "通过点击，直接选中",
      "keywords": [],
      "visibility": "public",
      "name": "clickHandler",
      "params": [
        {
          "name": "e",
          "type": "unknow",
          "rest": false
        },
        {
          "name": "index",
          "type": "unknow",
          "rest": false
        }
      ],
      "syntax": [
        "clickHandler(e: unknow, index: unknow): void"
      ],
      "returns": {
        "type": "void"
      }
    },
    {
      "kind": "method",
      "description": "发出事件",
      "keywords": [],
      "visibility": "public",
      "name": "emitEvent",
      "params": [],
      "syntax": [
        "emitEvent(): void"
      ],
      "returns": {
        "type": "void"
      }
    },
    {
      "kind": "method",
      "description": "获取当前激活的评分图标",
      "keywords": [],
      "visibility": "public",
      "name": "getActiveIndex",
      "params": [
        {
          "name": "x",
          "type": "unknow",
          "rest": false
        },
        {
          "name": "isClick",
          "type": "boolean",
          "defaultValue": "false",
          "rest": false
        }
      ],
      "syntax": [
        "getActiveIndex(x: unknow, isClick: boolean = false): void"
      ],
      "returns": {
        "type": "void"
      }
    }
  ],
  "name": "u-rate",
  "description": "#endif"
}